airtestProject/__init__.py
airtestProject/config.py
airtestProject/abstractBase/__init__.py
airtestProject/abstractBase/ai_base.py
airtestProject/abstractBase/operate_base.py
airtestProject/abstractBase/aiBaseImp/__init__.py
airtestProject/abstractBase/aiBaseImp/ai_base_imp.py
airtestProject/abstractBase/operateBaseImp/__init__.py
airtestProject/abstractBase/operateBaseImp/airtest_operate.py
airtestProject/abstractBase/operateBaseImp/ocr_operate.py
airtestProject/abstractBase/operateBaseImp/poco_operate.py
airtestProject/ai/__init__.py
airtestProject/airtest/__init__.py
airtestProject/airtest/__main__.py
airtestProject/airtest/aircv/__init__.py
airtestProject/airtest/aircv/aircv.py
airtestProject/airtest/aircv/cal_confidence.py
airtestProject/airtest/aircv/error.py
airtestProject/airtest/aircv/keypoint_base.py
airtestProject/airtest/aircv/keypoint_matching.py
airtestProject/airtest/aircv/keypoint_matching_contrib.py
airtestProject/airtest/aircv/multiscale_template_matching.py
airtestProject/airtest/aircv/screen_recorder.py
airtestProject/airtest/aircv/sift.py
airtestProject/airtest/aircv/template.py
airtestProject/airtest/aircv/template_matching.py
airtestProject/airtest/aircv/utils.py
airtestProject/airtest/cli/__init__.py
airtestProject/airtest/cli/__main__.py
airtestProject/airtest/cli/info.py
airtestProject/airtest/cli/parser.py
airtestProject/airtest/cli/runner.py
airtestProject/airtest/core/__init__.py
airtestProject/airtest/core/api.py
airtestProject/airtest/core/assertions.py
airtestProject/airtest/core/cv.py
airtestProject/airtest/core/device.py
airtestProject/airtest/core/error.py
airtestProject/airtest/core/helper.py
airtestProject/airtest/core/settings.py
airtestProject/airtest/core/android/__init__.py
airtestProject/airtest/core/android/adb.py
airtestProject/airtest/core/android/android.py
airtestProject/airtest/core/android/constant.py
airtestProject/airtest/core/android/ime.py
airtestProject/airtest/core/android/recorder.py
airtestProject-0.2.55.dist-info/LICENSE
airtestProject-0.2.55.dist-info/METADATA
airtestProject-0.2.55.dist-info/WHEEL
airtestProject-0.2.55.dist-info/top_level.txt
airtestProject-0.2.55.dist-info/RECORD
