Metadata-Version: 2.1
Name: airtestProject
Version: 0.2.55
Author: mortal_sjh
Author-email: mortal_sjh@qq.com
Requires-Python: >=3.9
License-File: LICENSE
Requires-Dist: openpyxl==3.1.4
Requires-Dist: qrcode==7.4.2
Requires-Dist: watchdog==4.0.0
Requires-Dist: easyocr==1.7.1
Requires-Dist: paddleocr==2.7.3
Requires-Dist: loguru==0.5.3
Requires-Dist: paddlepaddle==2.6.1
Requires-Dist: numpy==1.22.4
Requires-Dist: torch==2.3.0
Requires-Dist: hrpc>=1.0.9
Requires-Dist: websocket-client==0.48.0
Requires-Dist: ffmpeg==1.4
Requires-Dist: xlwt==1.3.0
Requires-Dist: logzero==1.7.0
Requires-Dist: tidevice==0.12.9
Requires-Dist: pyautogui
Requires-Dist: pynput
Requires-Dist: pywin32
Requires-Dist: six
